python_tetris/__init__.py
python_tetris/ars
python_tetris/client.py
python_tetris/colors.py
python_tetris/main.py
python_tetris/network.py
python_tetris/py.typed
python_tetris/server.py
python_tetris/spirtesheet.py
python_tetris/tetris.py
python_tetris/tetromino.py
python_tetris-0.0.0.dist-info/METADATA
python_tetris-0.0.0.dist-info/WHEEL
python_tetris-0.0.0.dist-info/entry_points.txt
python_tetris-0.0.0.dist-info/top_level.txt
python_tetris-0.0.0.dist-info/RECORD
